Workbook
Name Slicer_Country: #N/A
Name Slicer_Years__Order_Date: #N/A

Sheet Sales Data
A1: Region | B1: Country | C1: Item Type | D1: Sales Channel | E1: Order Priority | F1: Order Date | G1: Order ID | H1: Ship Date | I1: Units Sold | J1: Unit Price | K1: Unit Cost | L1: Total Revenue | M1: Total Cost | N1: Total Profit
A2: Central America and the Caribbean | B2: Antigua and Barbuda | C2: Baby Food | D2: Online | E2: Medium | F2: 43819 | G2: 957081544 | H2: 43476 | I2: 552 | J2: 255.28 | K2: 159.42 | L2: 140914.56 | M2: 87999.84 | N2: 52914.72
A3: Central America and the Caribbean | B3: Panama | C3: Snacks | D3: Offline | E3: Cancelled | F3: 44747 | G3: 301644504 | H3: 44768 | I3: 2167 | J3: 152.58 | K3: 97.44 | L3: 330640.86 | M3: 211152.48 | N3: 119488.38
A4: Europe | B4: Czech Republic | C4: Beverages | D4: Offline | E4: Cancelled | F4: 44451 | G4: 478051030 | H4: 44468 | I4: 4778 | J4: 47.45 | K4: 31.79 | L4: 226716.1 | M4: 151892.62 | N4: 74823.48
A5: Asia | B5: North Korea | C5: Cereal | D5: Offline | E5: Low | F5: 44694 | G5: 892599952 | H5: 44727 | I5: 9016 | J5: 205.7 | K5: 117.11 | L5: 1854591.2 | M5: 1055863.8 | N5: 798727.44
A6: Asia | B6: Sri Lanka | C6: Snacks | D6: Offline | E6: Cancelled | F6: 42205 | G6: 571902596 | H6: 42212 | I6: 7542 | J6: 152.58 | K6: 97.44 | L6: 1150758.4 | M6: 734892.48 | N6: 415865.88
A7: Middle East and North Africa | B7: Morocco | C7: Personal Care | D7: Offline | E7: Low | F7: 44873 | G7: 412882792 | H7: 44887 | I7: 48 | J7: 81.73 | K7: 56.67 | L7: 3923.04 | M7: 2720.16 | N7: 1202.88
A8: Australia and Oceania | B8: Federated States of Micronesia | C8: Clothes | D8: Offline | E8: High | F8: 44283 | G8: 932776868 | H8: 44326 | I8: 8258 | J8: 109.28 | K8: 35.84 | L8: 902434.24 | M8: 295966.72 | N8: 606467.52
A9: Europe | B9: Bosnia and Herzegovina | C9: Clothes | D9: Online | E9: Medium | F9: 43752 | G9: 919133651 | H9: 43773 | I9: 927 | J9: 109.28 | K9: 35.84 | L9: 101302.56 | M9: 33223.68 | N9: 68078.88
A10: Middle East and North Africa | B10: Afghanistan | C10: Clothes | D10: Offline | E10: Medium | F10: 42609 | G10: 579814469 | H10: 42648 | I10: 8841 | J10: 109.28 | K10: 35.84 | L10: 966144.48 | M10: 316861.44 | N10: 649283.04
A11: Sub-Saharan Africa | B11: Ethiopia | C11: Baby Food | D11: Online | E11: Medium | F11: 42107 | G11: 192993152 | H11: 42131 | I11: 9817 | J11: 255.28 | K11: 159.42 | L11: 2506083.8 | M11: 1565026.1 | N11: 941057.62
A12: Middle East and North Africa | B12: Turkey | C12: Office Supplies | D12: Offline | E12: Cancelled | F12: 43733 | G12: 557156026 | H12: 43753 | I12: 3704 | J12: 651.21 | K12: 524.96 | L12: 2412081.8 | M12: 1944451.8 | N12: 467630
A13: Middle East and North Africa | B13: Oman | C13: Cosmetics | D13: Online | E13: Medium | F13: 43597 | G13: 741101920 | H13: 43602 | I13: 7382 | J13: 437.2 | K13: 263.33 | L13: 3227410.4 | M13: 1943902.1 | N13: 1283508.3
... A10001: Europe | B10001: Tanzania | C10001: Vegetables | D10001: Online | E10001: Low | F10001: 44385 | G10001: 996861922 | H10001: 44415 | I10001: 2450 | J10001: 154.06 | K10001: 90.93 | L10001: 377447 | M10001: 222778.5 | N10001: 154668.5

Sheet Extra Data
A1: Region | B1: Country | C1: Item Type | D1: Sales Channel | E1: Order Priority | F1: Order Date | G1: Order ID | H1: Ship Date | I1: Units Sold | J1: Unit Price | K1: Unit Cost | L1: Total Revenue | M1: Total Cost | N1: Total Profit
A2: Central America and the Caribbean | B2: Antigua and Barbuda | C2: Baby Food | D2: Online | E2: Medium | F2: 43819 | G2: 957081544 | H2: 43476 | I2: 552 | J2: 255.28 | K2: 159.42 | L2: 140914.56 | M2: 87999.84 | N2: 52914.72
A3: Central America and the Caribbean | B3: Panama | C3: Snacks | D3: Offline | E3: Cancelled | F3: 44747 | G3: 301644504 | H3: 44768 | I3: 2167 | J3: 152.58 | K3: 97.44 | L3: 330640.86 | M3: 211152.48 | N3: 119488.38
A4: Europe | B4: Czech Republic | C4: Beverages | D4: Offline | E4: Cancelled | F4: 44451 | G4: 478051030 | H4: 44468 | I4: 4778 | J4: 47.45 | K4: 31.79 | L4: 226716.1 | M4: 151892.62 | N4: 74823.48
A5: Asia | B5: North Korea | C5: Cereal | D5: Offline | E5: Low | F5: 44694 | G5: 892599952 | H5: 44727 | I5: 9016 | J5: 205.7 | K5: 117.11 | L5: 1854591.2 | M5: 1055863.8 | N5: 798727.44
A6: Asia | B6: Sri Lanka | C6: Snacks | D6: Offline | E6: Cancelled | F6: 42205 | G6: 571902596 | H6: 42212 | I6: 7542 | J6: 152.58 | K6: 97.44 | L6: 1150758.4 | M6: 734892.48 | N6: 415865.88
A7: Middle East and North Africa | B7: Morocco | C7: Personal Care | D7: Offline | E7: Low | F7: 44873 | G7: 412882792 | H7: 44887 | I7: 48 | J7: 81.73 | K7: 56.67 | L7: 3923.04 | M7: 2720.16 | N7: 1202.88
A8: Australia and Oceania | B8: Federated States of Micronesia | C8: Clothes | D8: Offline | E8: High | F8: 44283 | G8: 932776868 | H8: 44326 | I8: 8258 | J8: 109.28 | K8: 35.84 | L8: 902434.24 | M8: 295966.72 | N8: 606467.52
A9: Europe | B9: Bosnia and Herzegovina | C9: Clothes | D9: Online | E9: Medium | F9: 43752 | G9: 919133651 | H9: 43773 | I9: 927 | J9: 109.28 | K9: 35.84 | L9: 101302.56 | M9: 33223.68 | N9: 68078.88
A10: Middle East and North Africa | B10: Afghanistan | C10: Clothes | D10: Offline | E10: Medium | F10: 42609 | G10: 579814469 | H10: 42648 | I10: 8841 | J10: 109.28 | K10: 35.84 | L10: 966144.48 | M10: 316861.44 | N10: 649283.04
A11: Europe | B11: Ethiopia | C11: Baby Food | D11: Online | E11: Medium | F11: 42107 | G11: 192993152 | H11: 42131 | I11: 9817 | J11: 255.28 | K11: 159.42 | L11: 2506083.8 | M11: 1565026.1 | N11: 941057.62
A12: Middle East and North Africa | B12: Turkey | C12: Office Supplies | D12: Offline | E12: Cancelled | F12: 43733 | G12: 557156026 | H12: 43753 | I12: 3704 | J12: 651.21 | K12: 524.96 | L12: 2412081.8 | M12: 1944451.8 | N12: 467630
A13: Middle East and North Africa | B13: Oman | C13: Cosmetics | D13: Online | E13: Medium | F13: 43597 | G13: 741101920 | H13: 43602 | I13: 7382 | J13: 437.2 | K13: 263.33 | L13: 3227410.4 | M13: 1943902.1 | N13: 1283508.3
... A5001: Europe | B5001: Tanzania | C5001: Vegetables | D5001: Online | E5001: Low | F5001: 44385 | G5001: 996861922 | H5001: 44415 | I5001: 2450 | J5001: 154.06 | K5001: 90.93 | L5001: 377447 | M5001: 222778.5 | N5001: 154668.5

Sheet Month by Revenue
A3: Row Labels | B3: Sum of Total Revenue
A4: Jan | B4: 6.52555e+08
A5: Feb | B5: 5.2768517e+08
A6: Mar | B6: 5.6072237e+08
A7: Apr | B7: 5.3608092e+08
A8: May | B8: 6.1757283e+08
A9: Jun | B9: 5.801497e+08
A10: Jul | B10: 5.9052319e+08
A11: Aug | B11: 5.3163457e+08
A12: Sep | B12: 4.8670664e+08
A13: Oct | B13: 5.0503098e+08
A14: Nov | B14: 5.1093026e+08
A15: Dec | B15: 5.2909759e+08
A16: Grand Total | B16: 6.6286892e+09

Sheet Item Type by Revenue
A3: Item Type | B3: Total_Revenue
A4: Baby Food | B4: 5.8074183e+08
A5: Beverages | B5: 1.0477762e+08
A6: Cereal | B6: 4.0103293e+08
A7: Clothes | B7: 2.1675087e+08
A8: Cosmetics | B8: 9.3644261e+08
A9: Fruits | B9: 21842304
A10: Household | B10: 1.4028578e+09
A11: Meat | B11: 8.02096e+08
A12: Office Supplies | B12: 1.3725084e+09
A13: Personal Care | B13: 1.7448497e+08
A14: Snacks | B14: 2.9311762e+08
A15: Vegetables | B15: 3.2203624e+08
A16: Grand Total | B16: 6.6286892e+09

Sheet Region by Revenue
A3: Region | B3: Total_Revenue
A4: Asia | B4: 9.2027709e+08
A5: Australia and Oceania | B5: 5.8736409e+08
A6: Central America and the Caribbean | B6: 6.8497632e+08
A7: Europe | B7: 1.7036224e+09
A8: Middle East and North Africa | B8: 7.6686778e+08
A9: North America | B9: 1.5101425e+08
A10: Sub-Saharan Africa | B10: 1.8145673e+09
A11: Grand Total | B11: 6.6286892e+09

Sheet Order Priority by Revenue
A3: Order Priority | B3: Total_Revenue
A4: Cancelled | B4: 1.5755966e+09
A5: High | B5: 1.712911e+09
A6: Low | B6: 1.5589143e+09
A7: Medium | B7: 1.7812673e+09
A8: Grand Total | B8: 6.6286892e+09

Sheet Calculations
A1: Calculations
A3: Key Metrics
B4: ITEM TYPE | C4: TOTAL PROFIT PER ITEM | E4: REGION | F4: TOTAL PROFIT PER REGION | H4: COUNT OF CANCELLED ORDERS
A5: Most Profitable Item | B5: {=_xlfn.UNIQUE(Sales_Data[Item Type])} -> Baby Food | C5: =SUMIF(Sales_Data[Item Type],Calculations!B5,Sales_Data[Total Profit]) -> 4.3614785e+08 | E5: {=_xlfn.UNIQUE(Sales_Data[Region])} -> Central America and the Caribbean | F5: =SUMIF(Sales_Data[Region],Calculations!E5,Sales_Data[Total Profit]) -> 4.0922396e+08 | H5: =COUNTIF(Sales_Data[Order Priority],'Sales Data'!E4988) -> 2348
A6: Most Profitable Region | B6: Snacks | C6: =SUMIF(Sales_Data[Item Type],Calculations!B6,Sales_Data[Total Profit]) -> 2.1185615e+08 | E6: Europe | F6: =SUMIF(Sales_Data[Region],Calculations!E6,Sales_Data[Total Profit]) -> 1.5344944e+09
A7: Count of Cancelled Orders | B7: Beverages | C7: =SUMIF(Sales_Data[Item Type],Calculations!B7,Sales_Data[Total Profit]) -> 69159853 | E7: Asia | F7: =SUMIF(Sales_Data[Region],Calculations!E7,Sales_Data[Total Profit]) -> 5.5647532e+08
A8: Top Sales Channel | B8: Cereal | C8: =SUMIF(Sales_Data[Item Type],Calculations!B8,Sales_Data[Total Profit]) -> 3.4543031e+08 | E8: Middle East and North Africa | F8: =SUMIF(Sales_Data[Region],Calculations!E8,Sales_Data[Total Profit]) -> 4.627606e+08 | H8: SALES CHANNEL | I8: COUNT OF SALES CHANNEL
B9: Personal Care | C9: =SUMIF(Sales_Data[Item Type],Calculations!B9,Sales_Data[Total Profit]) -> 1.0700094e+08 | E9: Australia and Oceania | F9: =SUMIF(Sales_Data[Region],Calculations!E9,Sales_Data[Total Profit]) -> 3.4986915e+08 | H9: {=_xlfn.UNIQUE(Sales_Data[Sales Channel])} -> Online | I9: =COUNTIF(Sales_Data[Sales Channel],Calculations!H9) -> 4992
B10: Clothes | C10: =SUMIF(Sales_Data[Item Type],Calculations!B10,Sales_Data[Total Profit]) -> 2.913284e+08 | E10: Sub-Saharan Africa | F10: =SUMIF(Sales_Data[Region],Calculations!E10,Sales_Data[Total Profit]) -> 5.3114227e+08 | H10: Offline | I10: =COUNTIF(Sales_Data[Sales Channel],Calculations!H10) -> 5008
B11: Office Supplies | C11: =SUMIF(Sales_Data[Item Type],Calculations!B11,Sales_Data[Total Profit]) -> 532176070 | E11: North America | F11: =SUMIF(Sales_Data[Region],Calculations!E11,Sales_Data[Total Profit]) -> 82480796
B12: Cosmetics | C12: =SUMIF(Sales_Data[Item Type],Calculations!B12,Sales_Data[Total Profit]) -> 7.4482744e+08
B13: Meat | C13: =SUMIF(Sales_Data[Item Type],Calculations!B13,Sales_Data[Total Profit]) -> 2.1749694e+08
B14: Fruits | C14: =SUMIF(Sales_Data[Item Type],Calculations!B14,Sales_Data[Total Profit]) -> 11284020
B15: Vegetables | C15: =SUMIF(Sales_Data[Item Type],Calculations!B15,Sales_Data[Total Profit]) -> 2.6392507e+08
B16: Household | C16: =SUMIF(Sales_Data[Item Type],Calculations!B16,Sales_Data[Total Profit]) -> 6.9581343e+08
B19: MOST PROFITABLE ITEM | C19: {=INDEX(B5:C16,MATCH(C20,C5:C16,0),)} -> Cosmetics | D19: 7.4482744e+08 | E19: M0ST PROFITABLE REGION | F19: {=_xlfn.XLOOKUP(F20,F5:F11,_xlfn.ANCHORARRAY(E5))} -> Europe | H19: MOST PROFITABLE SALES CHANNEL | I19: {=INDEX(H9:I10,MATCH(I20,I9:I10,1),)} -> Offline | J19: 5008
B20: VALUE | C20: =MAX(C5:C16) -> 7.4482744e+08 | E20: VALUE | F20: =MAX(F5:F11) -> 1.5344944e+09 | H20: VALUE | I20: =MAX(I9:I10) -> 5008

Sheet Dashboard
B1: PRODUCT SALES DASHBOARD (2015-2022)
